snakeddos/__init__.py
snakeddos/applications.py
snakeddos/consts.py
snakeddos/exceptions.py
snakeddos-0.0.6.dist-info/METADATA
snakeddos-0.0.6.dist-info/WHEEL
snakeddos-0.0.6.dist-info/licenses/LICENSE
snakeddos-0.0.6.dist-info/RECORD
